{"files":[{"culture":null,"installRoot":null,"ngen":null,"path":"obj\\Debug\\TemplateManifests\\templateManifest0.1033.vstman","targetPath":null,"vsixSubPath":"ItemTemplates"},{"culture":null,"installRoot":null,"ngen":null,"path":"obj\\Debug\\ItemTemplates\\CSharp\\1033\\CommentReviewRate\\CSharp.vstemplate","targetPath":"","vsixSubPath":"ItemTemplates\\CSharp\\1033\\CommentReviewRate"},{"culture":null,"installRoot":null,"ngen":null,"path":"obj\\Debug\\ItemTemplates\\CSharp\\1033\\CommentReviewRate\\crr.crr","targetPath":"","vsixSubPath":"ItemTemplates\\CSharp\\1033\\CommentReviewRate"},{"culture":null,"installRoot":null,"ngen":null,"path":"obj\\Debug\\ItemTemplates\\CSharp\\1033\\CommentReviewRate\\crr.diagram","targetPath":"","vsixSubPath":"ItemTemplates\\CSharp\\1033\\CommentReviewRate"},{"culture":null,"installRoot":null,"ngen":null,"path":"obj\\Debug\\ItemTemplates\\VisualBasic\\1033\\CommentReviewRate\\VisualBasic.vstemplate","targetPath":"","vsixSubPath":"ItemTemplates\\VisualBasic\\1033\\CommentReviewRate"},{"culture":null,"installRoot":null,"ngen":null,"path":"obj\\Debug\\ItemTemplates\\VisualBasic\\1033\\CommentReviewRate\\crr.crr","targetPath":"","vsixSubPath":"ItemTemplates\\VisualBasic\\1033\\CommentReviewRate"},{"culture":null,"installRoot":null,"ngen":null,"path":"obj\\Debug\\ItemTemplates\\VisualBasic\\1033\\CommentReviewRate\\crr.diagram","targetPath":"","vsixSubPath":"ItemTemplates\\VisualBasic\\1033\\CommentReviewRate"}]}